<?xml version="1.0" encoding="utf-8"?>
<key id="4d959b59-f987-4492-89ae-7ac9b9ecbe35" version="1">
  <creationDate>2020-07-18T14:00:43.5459613Z</creationDate>
  <activationDate>2020-07-18T14:00:43.512741Z</activationDate>
  <expirationDate>2020-10-16T14:00:43.512741Z</expirationDate>
  <descriptor deserializerType="Microsoft.AspNetCore.DataProtection.AuthenticatedEncryption.ConfigurationModel.AuthenticatedEncryptorDescriptorDeserializer, Microsoft.AspNetCore.DataProtection, Version=3.1.6.0, Culture=neutral, PublicKeyToken=adb9793829ddae60">
    <descriptor>
      <encryption algorithm="AES_256_CBC" />
      <validation algorithm="HMACSHA256" />
      <masterKey p4:requiresEncryption="true" xmlns:p4="http://schemas.asp.net/2015/03/dataProtection">
        <!-- Warning: the key below is in an unencrypted form. -->
        <value>3x8gLAsyyYo6bYjGxxrHCH4Z8ndWiTPCQG4Jraxw9YPLNu4/1sn5ESpZLv/G4ul+ttSPH5allmflMA9LFSy3yA==</value>
      </masterKey>
    </descriptor>
  </descriptor>
</key>